snyk_threadfix/__init__.py
snyk_threadfix/main.py
snyk_threadfix/utils.py
snyk_threadfix-0.0.6.dist-info/entry_points.txt
snyk_threadfix-0.0.6.dist-info/LICENSE
snyk_threadfix-0.0.6.dist-info/WHEEL
snyk_threadfix-0.0.6.dist-info/METADATA
snyk_threadfix-0.0.6.dist-info/RECORD
