Metadata-Version: 2.1
Name: snyk-threadfix
Version: 0.0.6
Summary: 
Home-page: https://github.com/snyk-labs/snyk-threadfix
License: Apache-2.0
Author: Jeff McLean
Author-email: jeff@snyk.io
Requires-Python: >=3.7,<4.0
Classifier: License :: OSI Approved :: Apache Software License
Classifier: Programming Language :: Python :: 3
Classifier: Programming Language :: Python :: 3.10
Classifier: Programming Language :: Python :: 3.7
Classifier: Programming Language :: Python :: 3.8
Classifier: Programming Language :: Python :: 3.9
Requires-Dist: arrow
Requires-Dist: importlib-metadata (>=4.11.2,<5.0.0)
Requires-Dist: pysnyk (>=0.8.1,<0.9.0)
Project-URL: Repository, https://github.com/snyk-labs/snyk-threadfix
